LICENSE
MANIFEST.in
README.md
setup.cfg
setup.py
ekankthk3x/__init__.py
ekankthk3x/config.py
ekankthk3x.egg-info/PKG-INFO
ekankthk3x.egg-info/SOURCES.txt
ekankthk3x.egg-info/dependency_links.txt
ekankthk3x.egg-info/requires.txt
ekankthk3x.egg-info/top_level.txt
ekankthk3x/Clients/__init__.py
ekankthk3x/Clients/client.py
ekankthk3x/Clients/pytgcalls.py
ekankthk3x/blacklist/__init__.py
ekankthk3x/blacklist/support.py
ekankthk3x/button/__init__.py
ekankthk3x/button/button.py
ekankthk3x/extra/__init__.py
ekankthk3x/extra/hosted.py
ekankthk3x/help/__init__.py
ekankthk3x/help/help.py
ekankthk3x/helper/__init__.py
ekankthk3x/helper/basic.py
ekankthk3x/helper/call.py
ekankthk3x/helper/data.py
ekankthk3x/helper/ekankth.py
ekankthk3x/helper/goblok.py
ekankthk3x/helper/hacking.py
ekankthk3x/helper/inline.py
ekankthk3x/helper/interval.py
ekankthk3x/helper/parser.py
ekankthk3x/helper/repo.py
ekankthk3x/helper/sticker.py
ekankthk3x/helper/tools.py
ekankthk3x/helper/utility.py
ekankthk3x/helper/what.py
ekankthk3x/methods/__init__.py
ekankthk3x/methods/queue.py
ekankthk3x/py_trans/__init__.py
ekankthk3x/py_trans/async_translator.py
ekankthk3x/py_trans/errors.py
ekankthk3x/py_trans/language_codes.py
ekankthk3x/py_trans/translator.py
ekankthk3x/pyrogram/__init__.py
ekankthk3x/pyrogram/_wrappers.py
ekankthk3x/pyrogram/func.py
ekankthk3x/pyrogram/misc.py
ekankthk3x/pyrogram/sections.py
ekankthk3x/pyrogram/toolbot.py
ekankthk3x/pyrogram/tools.py